hnvlearn/__init__.py
hnvlearn/datasets.py
hnvlearn/make_blobs.py
hnvlearn/plot_2d_separator.py
hnvlearn/plot_agglomerative.py
hnvlearn/plot_animal_tree.py
hnvlearn/plot_cross_validation.py
hnvlearn/plot_dbscan.py
hnvlearn/plot_decomposition.py
hnvlearn/plot_grid_search.py
hnvlearn/plot_helpers.py
hnvlearn/plot_improper_preprocessing.py
hnvlearn/plot_interactive_tree.py
hnvlearn/plot_kmeans.py
hnvlearn/plot_kneighbors_regularization.py
hnvlearn/plot_knn_classification.py
hnvlearn/plot_knn_regression.py
hnvlearn/plot_linear_regression.py
hnvlearn/plot_linear_svc_regularization.py
hnvlearn/plot_metrics.py
hnvlearn/plot_nmf.py
hnvlearn/plot_nn_graphs.py
hnvlearn/plot_pca.py
hnvlearn/plot_rbf_svm_parameters.py
hnvlearn/plot_ridge.py
hnvlearn/plot_scaling.py
hnvlearn/plot_tree_nonmonotonous.py
hnvlearn/plots.py
hnvlearn/tools.py
hnvlearn-0.0.3.dist-info/METADATA
hnvlearn-0.0.3.dist-info/WHEEL
hnvlearn-0.0.3.dist-info/top_level.txt
hnvlearn-0.0.3.dist-info/RECORD
