Metadata-Version: 2.1
Name: hnvlearn
Version: 0.0.3
Summary: hnvlearn Python library
Home-page: https://github.com/Vikram-kr/hnvlearn
Author: hnvlearn
Author-email: hnv@hnv.com
Classifier: Development Status :: 3 - Alpha
Classifier: Intended Audience :: Developers
Classifier: License :: OSI Approved :: MIT License
Classifier: Programming Language :: Python :: 3
Classifier: Programming Language :: Python :: 3.6
Classifier: Programming Language :: Python :: 3.7
Classifier: Programming Language :: Python :: 3.8
Classifier: Programming Language :: Python :: 3.9
Requires-Dist: numpy (>=1.22.4)
Requires-Dist: pandas (>=1.4.4)
Requires-Dist: matplotlib (>=3.7.1)
Requires-Dist: scikit-learn (>=1.2.2)
Requires-Dist: scipy (>=1.10.1)
Requires-Dist: ipython (>=7.34.0)
